moviepilot_mcp/__init__.py
moviepilot_mcp/auth.py
moviepilot_mcp/movie_pilot_client.py
moviepilot_mcp/remote_server.py
moviepilot_mcp/server.py
moviepilot_mcp/apis/__init__.py
moviepilot_mcp/apis/discover.py
moviepilot_mcp/apis/media.py
moviepilot_mcp/apis/media_server.py
moviepilot_mcp/apis/recommend.py
moviepilot_mcp/apis/search.py
moviepilot_mcp/apis/suscribe.py
moviepilot_mcp/schemas/__init__.py
moviepilot_mcp/schemas/douban_discover.py
moviepilot_mcp/schemas/recommend.py
moviepilot_mcp/schemas/subscribe.py
moviepilot_mcp/schemas/tmdb_discover.py
moviepilot_mcp-0.1.13.dist-info/METADATA
moviepilot_mcp-0.1.13.dist-info/WHEEL
moviepilot_mcp-0.1.13.dist-info/entry_points.txt
moviepilot_mcp-0.1.13.dist-info/licenses/LICENSE
moviepilot_mcp-0.1.13.dist-info/RECORD
