Metadata-Version: 2.4
Name: moviepilot-mcp
Version: 0.1.13
Summary: MoviePilot MCP 服务器，连接大型语言模型与MoviePilot媒体库管理系统
Project-URL: Homepage, https://github.com/Pollo3470/MoviePilot-MCP
License: MIT
License-File: LICENSE
Classifier: Development Status :: 4 - Beta
Classifier: Intended Audience :: Developers
Classifier: License :: OSI Approved :: MIT License
Classifier: Programming Language :: Python :: 3
Classifier: Programming Language :: Python :: 3.12
Requires-Python: >=3.12
Requires-Dist: fastmcp>=2.3.3
Requires-Dist: httpx[http2]>=0.28.1
Requires-Dist: pydantic>=2.11.4
Requires-Dist: pyyaml>=6.0.2
Requires-Dist: uvicorn>=0.34.1
